Metadata-Version: 1.1
Name: httpie-aws-auth
Version: 0.0.3
Summary: AWS/S3 auth plugin for HTTPie.
Home-page: https://github.com/jkbrzt/httpie-aws-auth
Author: Jakub Roztocil
Author-email: jakub@roztocil.co
License: BSD
Download-URL: https://github.com/jkbrzt/httpie-aws-auth
Platform: UNKNOWN
Classifier: Development Status :: 5 - Production/Stable
Classifier: Programming Language :: Python
Classifier: Programming Language :: Python :: 2
Classifier: Programming Language :: Python :: 2.6
Classifier: Programming Language :: Python :: 2.7
Classifier: Programming Language :: Python :: 3
Classifier: Programming Language :: Python :: 3.3
Classifier: Programming Language :: Python :: 3.4
Classifier: Environment :: Plugins
Classifier: License :: OSI Approved :: BSD License
Classifier: Topic :: Internet :: WWW/HTTP
Classifier: Topic :: Utilities
